[
    {
        "name": "glass_beach",
        "id": "0",
        "elems": 
        [
            {
                "name": "glass_beach", 
                "src": "./punk/traits/img/male/glass/glass_beach_mount.png", 
                "thikness": 1, 
                "z": 1
            },
            {
                "name": "glass_beach_glass", 
                "src": "./punk/traits/img/male/glass/glass_beach_glass.png", 
                "thikness": 0, 
                "z": 1.5,
                "opacity": 0.7, 
                "isMerged": true
            }
        ]
    },
    {
        "name": "glass02",
        "id": "1",
        "elems": 
        [
            {
                "name": "glass02_mount", 
                "src": "./punk/traits/img/male/glass/glass02_mount.png", 
                "thikness": 1, 
                "z": 1
            },
            {
                "name": "glass02_glass", 
                "src": "./punk/traits/img/male/glass/glass02_glass.png", 
                "thikness": 0, 
                "z": 1.5,
                "opacity": 0.7, 
                "isMerged": true
            }
        ]
    },
    {
        "name": "glass03",
        "id": "2",
        "elems": 
        [
            {
                "name": "glass03_mount", 
                "src": "./punk/traits/img/male/glass/glass03_mount.png", 
                "thikness": 1, 
                "z": 1
            },
            {
                "name": "glass03_glass", 
                "src": "./punk/traits/img/male/glass/glass03_glass.png", 
                "thikness": 0, 
                "z": 1.5,
                "opacity": 0.7, 
                "isMerged": true
            }
        ]
    },
    {
        "name": "glass04",
        "id": "3",
        "elems": 
        [
            {
                "name": "glass04_mount", 
                "src": "./punk/traits/img/male/glass/glass04_mount.png", 
                "thikness": 1, 
                "z": 1
            },
            {
                "name": "glass04_glass", 
                "src": "./punk/traits/img/male/glass/glass04_glass.png", 
                "thikness": 0, 
                "z": 1.5,
                "opacity": 0.7, 
                "isMerged": true
            }
        ]
    },
    {
        "name": "glass05",
        "id": "4",
        "elems": 
        [
            {
                "name": "glass05", 
                "src": "./punk/traits/img/male/glass/glass05.png", 
                "thikness": 1, 
                "z": 1
            }
        ]
    },
    {
        "name": "glass06",
        "id": "5",
        "elems": 
        [
            {
                "name": "glass06_mount", 
                "src": "./punk/traits/img/male/glass/glass06_mount.png", 
                "thikness": 1, 
                "z": 1
            },
            {
                "name": "glass06_glass", 
                "src": "./punk/traits/img/male/glass/glass06_glass.png", 
                "thikness": 0, 
                "z": 1.5,
                "opacity": 0.8, 
                "isMerged": true
            }
        ]
    },
    {
        "name": "glass07",
        "id": "6",
        "elems": 
        [
            {
                "name": "glass07b", 
                "src": "./punk/traits/img/male/glass/glass07a.png", 
                "thikness": 1, 
                "z": 1
            },
            {
                "name": "glass07a", 
                "src": "./punk/traits/img/male/glass/glass07b.png", 
                "thikness": 0, 
                "z": 1.5,
                "opacity": 0.8, 
                "isMerged": true
            }
        ]
    },
    {
        "name": "eyes_clown_blue",
        "id": "7",
        "elems": 
        [
            {
                "name": "eyes_clown_blue", 
                "src": "./punk/traits/img/male/glass/eyes_clown_blue.png", 
                "thikness": 1, 
                "z": 0
            }
        ]
    },
    {
        "name": "eyes_clown_green",
        "id": "8",
        "elems": 
        [
            {
                "name": "eyes_clown_green", 
                "src": "./punk/traits/img/male/glass/eyes_clown_green.png", 
                "thikness": 0.5, 
                "z": 1.5
            }
        ]
    },
    {
        "name": "glass_dbz",
        "id": "9",
        "elems": 
        [
            {
                "name": "hat_mickey_back", 
                "src": "./punk/traits/img/male/glass/glass_dbz_mount.png", 
                "thikness": 0.5, 
                "z": -1.75
            },
            {
                "name": "glass_dbz_mount", 
                "src": "./punk/traits/img/male/glass/glass_dbz_mount.png", 
                "thikness": 1, 
                "z": -1
            },
            {
                "name": "glass_dbz_mount", 
                "src": "./punk/traits/img/male/glass/glass_dbz_mount.png", 
                "thikness": 1, 
                "z": 0
            },
            {
                "name": "glass_dbz_mount", 
                "src": "./punk/traits/img/male/glass/glass_dbz_mount.png", 
                "thikness": 1, 
                "z": 1
            },
            {
                "name": "glass_dbz_glass", 
                "src": "./punk/traits/img/male/glass/glass_dbz_glass.png", 
                "thikness": 0, 
                "z": 1.5,
                "opacity": 0.8, 
                "isMerged": true
            }
        ]
    }
]